programGUI/__init__.py
programGUI-1.4.dist-info/METADATA
programGUI-1.4.dist-info/WHEEL
programGUI-1.4.dist-info/top_level.txt
programGUI-1.4.dist-info/zip-safe
programGUI-1.4.dist-info/RECORD
