Metadata-Version: 2.1
Name: programGUI
Version: 1.4
Summary: Makes it easy to start your application in GUI mode.
Home-page: https://github.com/CastellaniDavide/programGUI
Author: CastellaniDavide
Author-email: help@castellanidavide.it
License: GNU
Platform: linux_distibution
Requires-Python: >=3.7
Requires-Dist: PySimpleGUI
